slimpy/__init__.py
slimpy/core.py
slimpy/rematch.py
slimpy-0.1.0.dist-info/METADATA
slimpy-0.1.0.dist-info/WHEEL
slimpy-0.1.0.dist-info/licenses/LICENSE
slimpy-0.1.0.dist-info/RECORD
