Metadata-Version: 2.1
Name: slimpy
Version: 0.1.0
Summary: Custom String Slicing and Matching in Python
Project-URL: Homepage, https://github.com/max-efort/slimpy
Author-email: Jibril <erikfortran@gmail.com>
License: MIT License
License-File: LICENSE
Keywords: matching,mismatch,slicing
Classifier: Development Status :: 5 - Production/Stable
Classifier: Intended Audience :: Developers
Classifier: License :: OSI Approved :: MIT License
Classifier: Programming Language :: Python :: 3
Classifier: Topic :: Software Development :: Libraries :: Python Modules
Requires-Python: >=3.6
